qgbot/__init__.py
qgbot/config_loader.py
qgbot/core.py
qgbot/db.py
qgbot/executor.py
qgbot/grid.py
qgbot/main.py
qgbot/rebalance.py
qgbot/scorer.py
qgbot/utils.py
qgbot/wallet.py
quantgridbot-2.3.1.dist-info/licenses/LICENSE
quantgridbot-2.3.1.dist-info/METADATA
quantgridbot-2.3.1.dist-info/WHEEL
quantgridbot-2.3.1.dist-info/entry_points.txt
quantgridbot-2.3.1.dist-info/top_level.txt
quantgridbot-2.3.1.dist-info/RECORD
