Metadata-Version: 2.4
Name: quantgridbot
Version: 2.3.1
Summary: Quant-Grade Dynamic Ethereum Grid Trading and Intelligent Portfolio Rebalancing Engine with Live Dashboard Monitoring and Resilient Execution
Home-page: https://github.com/LoQiseaking69/qgbot
Author: LoQiseaking69
Author-email: LoQiseaking69 <REEL0112359.13@proton.me>
License: BSD-3-Clause
Project-URL: Homepage, https://github.com/LoQiseaking69/qgbot
Project-URL: Repository, https://github.com/LoQiseaking69/qgbot
Keywords: ethereum,grid trading,dynamic trading bot,portfolio rebalancing,quantitative trading,volatility trading,decentralized finance,crypto trading bot,uniswap bot,eth bot,python trading bot,autonomous trading,real-time dashboard,eth grid bot,live monitoring
Classifier: Programming Language :: Python :: 3
Classifier: License :: OSI Approved :: BSD License
Classifier: Operating System :: OS Independent
Classifier: Development Status :: 5 - Production/Stable
Classifier: Intended Audience :: Developers
Classifier: Intended Audience :: Financial and Insurance Industry
Classifier: Topic :: Software Development :: Libraries
Classifier: Topic :: Office/Business :: Financial
Classifier: Topic :: Scientific/Engineering :: Artificial Intelligence
Classifier: Topic :: Scientific/Engineering :: Information Analysis
Requires-Python: >=3.9
License-File: LICENSE
Requires-Dist: numpy>=1.23
Requires-Dist: ecdsa>=0.18
Requires-Dist: requests>=2.28
Requires-Dist: psutil>=5.9
Requires-Dist: rich>=13.0
Requires-Dist: eth-utils>=2.1.0
Dynamic: author
Dynamic: home-page
Dynamic: license-file
Dynamic: requires-python
